sqlsymphony_orm/__init__.py
sqlsymphony_orm/constants.py
sqlsymphony_orm/database/connection.py
sqlsymphony_orm/database/manager.py
sqlsymphony_orm/datatypes/fields.py
sqlsymphony_orm/exceptions.py
sqlsymphony_orm/migrations/migrations_manager.py
sqlsymphony_orm/models/orm_models.py
sqlsymphony_orm/models/session_models.py
sqlsymphony_orm/patterns.py
sqlsymphony_orm/performance/cache.py
sqlsymphony_orm/queries.py
sqlsymphony_orm/security/hashing.py
sqlsymphony_orm/utils/auditing.py
sqlsymphony_orm/utils/slugger.py
sqlsymphony_orm-0.4.18.2.dist-info/METADATA
sqlsymphony_orm-0.4.18.2.dist-info/WHEEL
sqlsymphony_orm-0.4.18.2.dist-info/RECORD
