Metadata-Version: 2.1
Name: sqlsymphony_orm
Version: 0.4.18.2
Summary: The elegant and powerful SQLite3 ORM for Python
Author: alexeev-prog
Author-email: dev.alexeev@mail.ru
Requires-Python: >=3.8,<4.0
Classifier: Programming Language :: Python :: 3
Classifier: Programming Language :: Python :: 3.8
Classifier: Programming Language :: Python :: 3.9
Classifier: Programming Language :: Python :: 3.10
Classifier: Programming Language :: Python :: 3.11
Classifier: Programming Language :: Python :: 3.12
Requires-Dist: aiosqlite (>=0.20.0,<0.21.0)
Requires-Dist: click (>=8.1.7,<9.0.0)
Requires-Dist: loguru (>=0.7.2,<0.8.0)
Requires-Dist: pycolor-palette-loguru (>=0.2.0,<0.3.0)
Requires-Dist: pydantic (>=2.9.2,<3.0.0)
Requires-Dist: pytest (>=8.3.3,<9.0.0)
Requires-Dist: rich (>=13.9.2,<14.0.0)
Requires-Dist: ruff (>=0.6.9,<0.7.0)
